treeview/__init__.py
treeview/treeview.py
treeview/dbase/__init__.py
treeview/dbase/datab.py
treeview/tvdescript/__init__.py
treeview/tvdescript/tvdescript.py
treeview_karjakak-1.8.5.dist-info/METADATA
treeview_karjakak-1.8.5.dist-info/WHEEL
treeview_karjakak-1.8.5.dist-info/top_level.txt
treeview_karjakak-1.8.5.dist-info/RECORD
