Metadata-Version: 2.1
Name: treeview-karjakak
Version: 1.8.5
Summary: TreeView is a note taking that written to text file and view in tree-view outline.
Home-page: https://github.com/kakkarja/TV
Author: karjakak
Author-email: kakkarja.github@gmail.com
License: BSD3 License
Classifier: Environment :: Win32 (MS Windows)
Classifier: Environment :: MacOS X
Classifier: Intended Audience :: End Users/Desktop
Classifier: Topic :: Text Editors :: Text Processing
Classifier: Programming Language :: Python :: 3.9
Classifier: License :: OSI Approved :: MIT License
Requires-Python: >=3.9
